{
  "updated_at": "2026-06-30T14:33:58.104650+00:00",
  "updated_display": "Jun 30, 2026 14:33 UTC",
  "sections": [
    {
      "title": "Equities 股票",
      "items": [
        {
          "key": "sp500",
          "name": "S&P 500",
          "sub": "USA",
          "price": "7,478.32",
          "chg": "+0.51%",
          "up": true,
          "chg_6m": "N/A",
          "up_6m": true,
          "chg_1y": "N/A",
          "up_1y": true,
          "chg_3y": "N/A",
          "up_3y": true,
          "range52": "6,177.97 – 7,620.90",
          "raw_price": 7478.31982421875
        },
        {
          "key": "nasdaq",
          "name": "NASDAQ",
          "sub": "USA Tech",
          "price": "26,083",
          "chg": "+1.02%",
          "up": true,
          "chg_6m": "N/A",
          "up_6m": true,
          "chg_1y": "N/A",
          "up_1y": true,
          "chg_3y": "N/A",
          "up_3y": true,
          "range52": "20,105 – 27,190",
          "raw_price": 26083.232421875
        },
        {
          "key": "nikkei",
          "name": "Nikkei 225",
          "sub": "Japan",
          "price": "70,062",
          "chg": "+0.98%",
          "up": true,
          "chg_6m": "N/A",
          "up_6m": true,
          "chg_1y": "N/A",
          "up_1y": true,
          "chg_3y": "N/A",
          "up_3y": true,
          "range52": "39,289 – 72,832",
          "raw_price": 70062.3203125
        },
        {
          "key": "csi1000",
          "name": "CSI 1000",
          "sub": "China",
          "price": "8,809.79",
          "chg": "+2.39%",
          "up": true,
          "chg_6m": "N/A",
          "up_6m": true,
          "chg_1y": "N/A",
          "up_1y": true,
          "chg_3y": "N/A",
          "up_3y": true,
          "range52": "8,547.31 – 8,815.11",
          "raw_price": 8809.7861328125
        },
        {
          "key": "hsi",
          "name": "Hang Seng",
          "sub": "Hong Kong",
          "price": "22,881",
          "chg": "-0.63%",
          "up": false,
          "chg_6m": "N/A",
          "up_6m": true,
          "chg_1y": "N/A",
          "up_1y": true,
          "chg_3y": "N/A",
          "up_3y": true,
          "range52": "22,518 – 28,056",
          "raw_price": 22881.01953125
        },
        {
          "key": "dax",
          "name": "DAX",
          "sub": "Germany",
          "price": "24,950",
          "chg": "+1.26%",
          "up": true,
          "chg_6m": "N/A",
          "up_6m": true,
          "chg_1y": "N/A",
          "up_1y": true,
          "chg_3y": "N/A",
          "up_3y": true,
          "range52": "21,864 – 25,508",
          "raw_price": 24949.619140625
        }
      ]
    },
    {
      "title": "Bonds 债券",
      "items": [
        {
          "key": "ust10",
          "name": "US 10Y Yield",
          "sub": "Treasury",
          "price": "4.40%",
          "chg": "+55bp",
          "up": true,
          "chg_6m": "N/A",
          "up_6m": true,
          "chg_1y": "N/A",
          "up_1y": true,
          "chg_3y": "N/A",
          "up_3y": true,
          "range52": "3.95% – 4.69%",
          "raw_price": 4.3979997634887695
        },
        {
          "key": "ust2",
          "name": "US 13W Yield",
          "sub": "Treasury",
          "price": "3.74%",
          "chg": "+163bp",
          "up": true,
          "chg_6m": "N/A",
          "up_6m": true,
          "chg_1y": "N/A",
          "up_1y": true,
          "chg_3y": "N/A",
          "up_3y": true,
          "range52": "3.51% – 4.25%",
          "raw_price": 3.7400002479553223
        }
      ]
    },
    {
      "title": "Commodities 商品",
      "items": [
        {
          "key": "gold",
          "name": "Gold",
          "sub": "XAU/USD",
          "price": "4,075.00",
          "chg": "+2.29%",
          "up": true,
          "chg_6m": "N/A",
          "up_6m": true,
          "chg_1y": "N/A",
          "up_1y": true,
          "chg_3y": "N/A",
          "up_3y": true,
          "range52": "3,263.90 – 5,586.20",
          "raw_price": 4075.0
        },
        {
          "key": "silver",
          "name": "Silver",
          "sub": "XAG/USD",
          "price": "60.6800",
          "chg": "+5.17%",
          "up": true,
          "chg_6m": "N/A",
          "up_6m": true,
          "chg_1y": "N/A",
          "up_1y": true,
          "chg_3y": "N/A",
          "up_3y": true,
          "range52": "35.8450 – 121.30",
          "raw_price": 60.68000030517578
        },
        {
          "key": "wti",
          "name": "WTI Crude",
          "sub": "Oil",
          "price": "70.6700",
          "chg": "+0.45%",
          "up": true,
          "chg_6m": "N/A",
          "up_6m": true,
          "chg_1y": "N/A",
          "up_1y": true,
          "chg_3y": "N/A",
          "up_3y": true,
          "range52": "54.9800 – 119.48",
          "raw_price": 70.66999816894531
        },
        {
          "key": "brent",
          "name": "Brent Crude",
          "sub": "Oil",
          "price": "74.0300",
          "chg": "+0.60%",
          "up": true,
          "chg_6m": "N/A",
          "up_6m": true,
          "chg_1y": "N/A",
          "up_1y": true,
          "chg_3y": "N/A",
          "up_3y": true,
          "range52": "58.7200 – 126.10",
          "raw_price": 74.02999877929688
        },
        {
          "key": "copper",
          "name": "Copper",
          "sub": "LME",
          "price": "6.3110",
          "chg": "+2.19%",
          "up": true,
          "chg_6m": "N/A",
          "up_6m": true,
          "chg_1y": "N/A",
          "up_1y": true,
          "chg_3y": "N/A",
          "up_3y": true,
          "range52": "4.3235 – 6.6525",
          "raw_price": 6.310999870300293
        },
        {
          "key": "natgas",
          "name": "Natural Gas",
          "sub": "NYMEX",
          "price": "3.2880",
          "chg": "+3.92%",
          "up": true,
          "chg_6m": "N/A",
          "up_6m": true,
          "chg_1y": "N/A",
          "up_1y": true,
          "chg_3y": "N/A",
          "up_3y": true,
          "range52": "2.4830 – 7.8270",
          "raw_price": 3.2880001068115234
        }
      ]
    },
    {
      "title": "Crypto 加密货币",
      "items": [
        {
          "key": "btc",
          "name": "Bitcoin",
          "sub": "BTC/USD",
          "price": "$58,865",
          "chg": "-1.08%",
          "up": false,
          "chg_6m": "N/A",
          "up_6m": true,
          "chg_1y": "N/A",
          "up_1y": true,
          "chg_3y": "N/A",
          "up_3y": true,
          "range52": "N/A",
          "raw_price": 58865
        },
        {
          "key": "eth",
          "name": "Ethereum",
          "sub": "ETH/USD",
          "price": "$1,571",
          "chg": "-0.07%",
          "up": false,
          "chg_6m": "N/A",
          "up_6m": true,
          "chg_1y": "N/A",
          "up_1y": true,
          "chg_3y": "N/A",
          "up_3y": true,
          "range52": "N/A",
          "raw_price": 1570.67
        },
        {
          "key": "sol",
          "name": "Solana",
          "sub": "SOL/USD",
          "price": "$73.57",
          "chg": "+0.62%",
          "up": true,
          "chg_6m": "N/A",
          "up_6m": true,
          "chg_1y": "N/A",
          "up_1y": true,
          "chg_3y": "N/A",
          "up_3y": true,
          "range52": "N/A",
          "raw_price": 73.57
        },
        {
          "key": "bnb",
          "name": "BNB",
          "sub": "BNB/USD",
          "price": "$548.66",
          "chg": "-0.20%",
          "up": false,
          "chg_6m": "N/A",
          "up_6m": true,
          "chg_1y": "N/A",
          "up_1y": true,
          "chg_3y": "N/A",
          "up_3y": true,
          "range52": "N/A",
          "raw_price": 548.66
        },
        {
          "key": "xrp",
          "name": "XRP",
          "sub": "XRP/USD",
          "price": "$1.04",
          "chg": "-0.17%",
          "up": false,
          "chg_6m": "N/A",
          "up_6m": true,
          "chg_1y": "N/A",
          "up_1y": true,
          "chg_3y": "N/A",
          "up_3y": true,
          "range52": "N/A",
          "raw_price": 1.042
        }
      ]
    },
    {
      "title": "FX 外汇",
      "items": [
        {
          "key": "eurusd",
          "name": "EUR/USD",
          "sub": "Euro / Dollar",
          "price": "1.1416",
          "chg": "-0.11%",
          "up": false,
          "chg_6m": "N/A",
          "up_6m": true,
          "chg_1y": "N/A",
          "up_1y": true,
          "chg_3y": "N/A",
          "up_3y": true,
          "range52": "1.1325 – 1.2024",
          "raw_price": 1.1415525674819946
        },
        {
          "key": "usdjpy",
          "name": "USD/JPY",
          "sub": "Dollar / Yen",
          "price": "162.417",
          "chg": "+0.30%",
          "up": true,
          "chg_6m": "N/A",
          "up_6m": true,
          "chg_1y": "N/A",
          "up_1y": true,
          "chg_3y": "N/A",
          "up_3y": true,
          "range52": "142.695 – 161.955",
          "raw_price": 162.41700744628906
        },
        {
          "key": "gbpusd",
          "name": "GBP/USD",
          "sub": "Cable",
          "price": "1.3240",
          "chg": "-0.17%",
          "up": false,
          "chg_6m": "N/A",
          "up_6m": true,
          "chg_1y": "N/A",
          "up_1y": true,
          "chg_3y": "N/A",
          "up_3y": true,
          "range52": "1.3012 – 1.3847",
          "raw_price": 1.324012279510498
        },
        {
          "key": "dxy",
          "name": "DXY",
          "sub": "Dollar Index",
          "price": "101.205",
          "chg": "-0.11%",
          "up": false,
          "chg_6m": "N/A",
          "up_6m": true,
          "chg_1y": "N/A",
          "up_1y": true,
          "chg_3y": "N/A",
          "up_3y": true,
          "range52": "95.550 – 101.800",
          "raw_price": 101.20500183105469
        },
        {
          "key": "usdcny",
          "name": "USD/CNY",
          "sub": "Offshore CNH",
          "price": "6.7751",
          "chg": "-0.17%",
          "up": false,
          "chg_6m": "N/A",
          "up_6m": true,
          "chg_1y": "N/A",
          "up_1y": true,
          "chg_3y": "N/A",
          "up_3y": true,
          "range52": "6.7570 – 7.2116",
          "raw_price": 6.775100231170654
        },
        {
          "key": "usdchf",
          "name": "USD/CHF",
          "sub": "Swissie",
          "price": "1.2372",
          "chg": "-0.11%",
          "up": false,
          "chg_6m": "N/A",
          "up_6m": true,
          "chg_1y": "N/A",
          "up_1y": true,
          "chg_3y": "N/A",
          "up_3y": true,
          "range52": "1.2239 – 1.3108",
          "raw_price": 1.2372409105300903
        }
      ]
    }
  ]
}