{
  "updated_at": "2026-06-12T15:31:59.545816+00:00",
  "updated_display": "Jun 12, 2026 15:31 UTC",
  "sections": [
    {
      "title": "Equities 股票",
      "items": [
        {
          "key": "sp500",
          "name": "S&P 500",
          "sub": "USA",
          "price": "7,447.13",
          "chg": "+0.73%",
          "up": true,
          "chg_6m": "N/A",
          "up_6m": true,
          "chg_1y": "N/A",
          "up_1y": true,
          "chg_3y": "N/A",
          "up_3y": true,
          "range52": "5,943.23 – 7,620.90",
          "raw_price": 7447.1298828125
        },
        {
          "key": "nasdaq",
          "name": "NASDAQ",
          "sub": "USA Tech",
          "price": "25,972",
          "chg": "+0.63%",
          "up": true,
          "chg_6m": "N/A",
          "up_6m": true,
          "chg_1y": "N/A",
          "up_1y": true,
          "chg_3y": "N/A",
          "up_3y": true,
          "range52": "19,335 – 27,190",
          "raw_price": 25971.90234375
        },
        {
          "key": "nikkei",
          "name": "Nikkei 225",
          "sub": "Japan",
          "price": "66,020",
          "chg": "+2.77%",
          "up": true,
          "chg_6m": "N/A",
          "up_6m": true,
          "chg_1y": "N/A",
          "up_1y": true,
          "chg_3y": "N/A",
          "up_3y": true,
          "range52": "38,026 – 68,786",
          "raw_price": 66020.04
        },
        {
          "key": "csi1000",
          "name": "CSI 1000",
          "sub": "China",
          "price": "8,202.80",
          "chg": "+0.50%",
          "up": true,
          "chg_6m": "N/A",
          "up_6m": true,
          "chg_1y": "N/A",
          "up_1y": true,
          "chg_3y": "N/A",
          "up_3y": true,
          "range52": "8,181.42 – 8,348.79",
          "raw_price": 8202.798828125
        },
        {
          "key": "hsi",
          "name": "Hang Seng",
          "sub": "Hong Kong",
          "price": "24,718",
          "chg": "+1.93%",
          "up": true,
          "chg_6m": "N/A",
          "up_6m": true,
          "chg_1y": "N/A",
          "up_1y": true,
          "chg_3y": "N/A",
          "up_3y": true,
          "range52": "23,186 – 28,056",
          "raw_price": 24718.099609375
        },
        {
          "key": "dax",
          "name": "DAX",
          "sub": "Germany",
          "price": "24,621",
          "chg": "+1.70%",
          "up": true,
          "chg_6m": "N/A",
          "up_6m": true,
          "chg_1y": "N/A",
          "up_1y": true,
          "chg_3y": "N/A",
          "up_3y": true,
          "range52": "21,864 – 25,508",
          "raw_price": 24621.01953125
        }
      ]
    },
    {
      "title": "Bonds 债券",
      "items": [
        {
          "key": "ust10",
          "name": "US 10Y Yield",
          "sub": "Treasury",
          "price": "4.48%",
          "chg": "+40bp",
          "up": true,
          "chg_6m": "N/A",
          "up_6m": true,
          "chg_1y": "N/A",
          "up_1y": true,
          "chg_3y": "N/A",
          "up_3y": true,
          "range52": "3.95% – 4.69%",
          "raw_price": 4.480999946594238
        },
        {
          "key": "ust2",
          "name": "US 13W Yield",
          "sub": "Treasury",
          "price": "3.62%",
          "chg": "+0bp",
          "up": true,
          "chg_6m": "N/A",
          "up_6m": true,
          "chg_1y": "N/A",
          "up_1y": true,
          "chg_3y": "N/A",
          "up_3y": true,
          "range52": "3.51% – 4.26%",
          "raw_price": 3.622999906539917
        }
      ]
    },
    {
      "title": "Commodities 商品",
      "items": [
        {
          "key": "gold",
          "name": "Gold",
          "sub": "XAU/USD",
          "price": "4,240.40",
          "chg": "+0.46%",
          "up": true,
          "chg_6m": "N/A",
          "up_6m": true,
          "chg_1y": "N/A",
          "up_1y": true,
          "chg_3y": "N/A",
          "up_3y": true,
          "range52": "3,253.80 – 5,586.20",
          "raw_price": 4240.39990234375
        },
        {
          "key": "silver",
          "name": "Silver",
          "sub": "XAG/USD",
          "price": "67.6500",
          "chg": "+0.55%",
          "up": true,
          "chg_6m": "N/A",
          "up_6m": true,
          "chg_1y": "N/A",
          "up_1y": true,
          "chg_3y": "N/A",
          "up_3y": true,
          "range52": "35.2700 – 121.30",
          "raw_price": 67.6500015258789
        },
        {
          "key": "wti",
          "name": "WTI Crude",
          "sub": "Oil",
          "price": "84.3800",
          "chg": "-2.20%",
          "up": false,
          "chg_6m": "N/A",
          "up_6m": true,
          "chg_1y": "N/A",
          "up_1y": true,
          "chg_3y": "N/A",
          "up_3y": true,
          "range52": "54.9800 – 119.48",
          "raw_price": 84.37999725341797
        },
        {
          "key": "brent",
          "name": "Brent Crude",
          "sub": "Oil",
          "price": "87.0100",
          "chg": "-2.02%",
          "up": false,
          "chg_6m": "N/A",
          "up_6m": true,
          "chg_1y": "N/A",
          "up_1y": true,
          "chg_3y": "N/A",
          "up_3y": true,
          "range52": "58.7200 – 126.10",
          "raw_price": 87.01000213623047
        },
        {
          "key": "copper",
          "name": "Copper",
          "sub": "LME",
          "price": "6.4360",
          "chg": "+0.16%",
          "up": true,
          "chg_6m": "N/A",
          "up_6m": true,
          "chg_1y": "N/A",
          "up_1y": true,
          "chg_3y": "N/A",
          "up_3y": true,
          "range52": "4.3235 – 6.6525",
          "raw_price": 6.435999870300293
        },
        {
          "key": "natgas",
          "name": "Natural Gas",
          "sub": "NYMEX",
          "price": "3.1090",
          "chg": "+1.24%",
          "up": true,
          "chg_6m": "N/A",
          "up_6m": true,
          "chg_1y": "N/A",
          "up_1y": true,
          "chg_3y": "N/A",
          "up_3y": true,
          "range52": "2.4830 – 7.8270",
          "raw_price": 3.1089999675750732
        }
      ]
    },
    {
      "title": "Crypto 加密货币",
      "items": [
        {
          "key": "btc",
          "name": "Bitcoin",
          "sub": "BTC/USD",
          "price": "$64,088",
          "chg": "+2.29%",
          "up": true,
          "chg_6m": "N/A",
          "up_6m": true,
          "chg_1y": "N/A",
          "up_1y": true,
          "chg_3y": "N/A",
          "up_3y": true,
          "range52": "N/A",
          "raw_price": 64088
        },
        {
          "key": "eth",
          "name": "Ethereum",
          "sub": "ETH/USD",
          "price": "$1,681",
          "chg": "+2.23%",
          "up": true,
          "chg_6m": "N/A",
          "up_6m": true,
          "chg_1y": "N/A",
          "up_1y": true,
          "chg_3y": "N/A",
          "up_3y": true,
          "range52": "N/A",
          "raw_price": 1680.63
        },
        {
          "key": "sol",
          "name": "Solana",
          "sub": "SOL/USD",
          "price": "$68.26",
          "chg": "+3.95%",
          "up": true,
          "chg_6m": "N/A",
          "up_6m": true,
          "chg_1y": "N/A",
          "up_1y": true,
          "chg_3y": "N/A",
          "up_3y": true,
          "range52": "N/A",
          "raw_price": 68.26
        },
        {
          "key": "bnb",
          "name": "BNB",
          "sub": "BNB/USD",
          "price": "$610.46",
          "chg": "+2.07%",
          "up": true,
          "chg_6m": "N/A",
          "up_6m": true,
          "chg_1y": "N/A",
          "up_1y": true,
          "chg_3y": "N/A",
          "up_3y": true,
          "range52": "N/A",
          "raw_price": 610.46
        },
        {
          "key": "xrp",
          "name": "XRP",
          "sub": "XRP/USD",
          "price": "$1.15",
          "chg": "+3.05%",
          "up": true,
          "chg_6m": "N/A",
          "up_6m": true,
          "chg_1y": "N/A",
          "up_1y": true,
          "chg_3y": "N/A",
          "up_3y": true,
          "range52": "N/A",
          "raw_price": 1.15
        }
      ]
    },
    {
      "title": "FX 外汇",
      "items": [
        {
          "key": "eurusd",
          "name": "EUR/USD",
          "sub": "Euro / Dollar",
          "price": "1.1586",
          "chg": "+0.00%",
          "up": true,
          "chg_6m": "N/A",
          "up_6m": true,
          "chg_1y": "N/A",
          "up_1y": true,
          "chg_3y": "N/A",
          "up_3y": true,
          "range52": "1.1395 – 1.2024",
          "raw_price": 1.1586142778396606
        },
        {
          "key": "usdjpy",
          "name": "USD/JPY",
          "sub": "Dollar / Yen",
          "price": "160.187",
          "chg": "+0.11%",
          "up": true,
          "chg_6m": "N/A",
          "up_6m": true,
          "chg_1y": "N/A",
          "up_1y": true,
          "chg_3y": "N/A",
          "up_3y": true,
          "range52": "142.695 – 160.702",
          "raw_price": 160.18699645996094
        },
        {
          "key": "gbpusd",
          "name": "GBP/USD",
          "sub": "Cable",
          "price": "1.3421",
          "chg": "-0.03%",
          "up": false,
          "chg_6m": "N/A",
          "up_6m": true,
          "chg_1y": "N/A",
          "up_1y": true,
          "chg_3y": "N/A",
          "up_3y": true,
          "range52": "1.3012 – 1.3847",
          "raw_price": 1.3420838117599487
        },
        {
          "key": "dxy",
          "name": "DXY",
          "sub": "Dollar Index",
          "price": "99.704",
          "chg": "-0.06%",
          "up": false,
          "chg_6m": "N/A",
          "up_6m": true,
          "chg_1y": "N/A",
          "up_1y": true,
          "chg_3y": "N/A",
          "up_3y": true,
          "range52": "95.550 – 100.640",
          "raw_price": 99.7040023803711
        },
        {
          "key": "usdcny",
          "name": "USD/CNY",
          "sub": "Offshore CNH",
          "price": "6.7621",
          "chg": "-0.19%",
          "up": false,
          "chg_6m": "N/A",
          "up_6m": true,
          "chg_1y": "N/A",
          "up_1y": true,
          "chg_3y": "N/A",
          "up_3y": true,
          "range52": "6.7622 – 7.2116",
          "raw_price": 6.7621002197265625
        },
        {
          "key": "usdchf",
          "name": "USD/CHF",
          "sub": "Swissie",
          "price": "1.2562",
          "chg": "-0.22%",
          "up": false,
          "chg_6m": "N/A",
          "up_6m": true,
          "chg_1y": "N/A",
          "up_1y": true,
          "chg_3y": "N/A",
          "up_3y": true,
          "range52": "1.2174 – 1.3108",
          "raw_price": 1.256234049797058
        }
      ]
    }
  ]
}